smem2/__init__.py
smem2/__main__.py
smem2/smem2.py
smem2-2.2.1.dist-info/METADATA
smem2-2.2.1.dist-info/WHEEL
smem2-2.2.1.dist-info/entry_points.txt
smem2-2.2.1.dist-info/licenses/COPYING
smem2-2.2.1.dist-info/RECORD
