Metadata-Version: 2.4
Name: smem2
Version: 2.2.1
Summary: A tool to monitor memory usage of processes and the system
Project-URL: Homepage, https://github.com/slhck/smem2
Project-URL: Issues, https://github.com/slhck/smem2/issues
Author-email: Werner Robitza <werner.robitza@gmail.com>
License-Expression: GPL-2.0-or-later
License-File: COPYING
Classifier: Operating System :: OS Independent
Classifier: Programming Language :: Python :: 3
Requires-Python: >=3.9
